password_generator/__init__.py
password_generator/generator.py
p_gen-0.0.5.dist-info/METADATA
p_gen-0.0.5.dist-info/WHEEL
p_gen-0.0.5.dist-info/entry_points.txt
p_gen-0.0.5.dist-info/top_level.txt
p_gen-0.0.5.dist-info/RECORD
