Metadata-Version: 2.1
Name: p-gen
Version: 0.0.5
Summary: A console utility that allows you to generate passwords based on code phrases and a secret key (seed).
Home-page: https://github.com/MaximZayats/password-generator
Author: Maxim
Author-email: maximzayats1@gmail.com
License: UNKNOWN
Platform: UNKNOWN
